difonlib/__init__.py
difonlib/bt_utils.py
difonlib/input_devs.py
difonlib/ng_lib.py
difonlib/py.typed
difonlib/remctrl.py
difonlib/tuya_devs.py
difonlib/utils.py
difonlib-0.2.2.dist-info/METADATA
difonlib-0.2.2.dist-info/WHEEL
difonlib-0.2.2.dist-info/top_level.txt
difonlib-0.2.2.dist-info/RECORD
