Metadata-Version: 2.4
Name: difonlib
Version: 0.2.2
Summary: python libraries
Requires-Python: >=3.10
Requires-Dist: evdev>=1.9.2
Requires-Dist: nicegui>=3.2.0
Requires-Dist: pexpect>=4.9.0
Requires-Dist: pyyaml>=6.0.3
Requires-Dist: tinytuya>=1.17.4
Requires-Dist: types-pexpect>=4.9.0.20250916
Requires-Dist: types-PyYAML>=6.0.12.20250915
Requires-Dist: types-xmltodict>=1.0.1.20250920
Requires-Dist: xmltodict>=1.0.2
